Metadata-Version: 2.1
Name: gffutils
Version: 0.13
Summary: Work with GFF and GTF files in a flexible database framework
Home-page: https://github.com/daler/gffutils
Author: Ryan Dale
Author-email: dalerr@niddk.nih.gov
Classifier: Intended Audience :: Science/Research
Classifier: License :: OSI Approved :: MIT License
Classifier: Topic :: Scientific/Engineering :: Bio-Informatics
Classifier: Programming Language :: Python
Classifier: Programming Language :: Python :: 2
Classifier: Programming Language :: Python :: 2.6
Classifier: Programming Language :: Python :: 2.7
Classifier: Programming Language :: Python :: 3
Classifier: Programming Language :: Python :: 3.3
Classifier: Programming Language :: Python :: 3.4
Classifier: Programming Language :: Python :: 3.5
Classifier: Programming Language :: Python :: 3.6
Classifier: Topic :: Software Development :: Libraries :: Python Modules
License-File: LICENSE
Requires-Dist: pyfaidx>=0.5.5.2
Requires-Dist: argh>=0.26.2
Requires-Dist: argcomplete>=1.9.4
Requires-Dist: simplejson
